climan/__init__.py
climan/climan.py
climanager-0.0.1.dist-info/LICENSE
climanager-0.0.1.dist-info/METADATA
climanager-0.0.1.dist-info/WHEEL
climanager-0.0.1.dist-info/top_level.txt
climanager-0.0.1.dist-info/RECORD
